{
  "annotations": {
    "list": [
      {
        "builtIn": 1,
        "datasource": {
          "type": "grafana",
          "uid": "-- Grafana --"
        },
        "enable": true,
        "hide": true,
        "iconColor": "rgba(0, 211, 255, 1)",
        "name": "Annotations & Alerts",
        "type": "dashboard"
      }
    ]
  },
  "editable": true,
  "fiscalYearStartMonth": 0,
  "graphTooltip": 0,
  "id": null,
  "links": [],
  "liveNow": false,
  "panels": [
    {
      "datasource": {
        "type": "loki",
        "uid": "Loki"
      },
      "description": "Current number of active rooms",
      "fieldConfig": {
        "defaults": {
          "color": {
            "mode": "thresholds"
          },
          "mappings": [],
          "thresholds": {
            "mode": "absolute",
            "steps": [
              {
                "color": "green",
                "value": null
              },
              {
                "color": "yellow",
                "value": 50
              },
              {
                "color": "red",
                "value": 100
              }
            ]
          },
          "unit": "short"
        },
        "overrides": []
      },
      "gridPos": {
        "h": 4,
        "w": 6,
        "x": 0,
        "y": 0
      },
      "id": 1,
      "options": {
        "colorMode": "background",
        "graphMode": "area",
        "justifyMode": "auto",
        "orientation": "auto",
        "reduceOptions": {
          "calcs": ["lastNotNull"],
          "fields": "",
          "values": false
        },
        "textMode": "auto"
      },
      "pluginVersion": "10.0.0",
      "targets": [
        {
          "datasource": {
            "type": "loki",
            "uid": "Loki"
          },
          "editorMode": "code",
          "expr": "{service=\"slam-poker\"} |= \"Room statistics snapshot\" | json | unwrap total_rooms",
          "queryType": "",
          "refId": "A"
        }
      ],
      "title": "Active Rooms",
      "type": "stat"
    },
    {
      "datasource": {
        "type": "loki",
        "uid": "Loki"
      },
      "description": "Current number of active users across all rooms",
      "fieldConfig": {
        "defaults": {
          "color": {
            "mode": "thresholds"
          },
          "mappings": [],
          "thresholds": {
            "mode": "absolute",
            "steps": [
              {
                "color": "green",
                "value": null
              },
              {
                "color": "yellow",
                "value": 200
              },
              {
                "color": "red",
                "value": 500
              }
            ]
          },
          "unit": "short"
        },
        "overrides": []
      },
      "gridPos": {
        "h": 4,
        "w": 6,
        "x": 6,
        "y": 0
      },
      "id": 2,
      "options": {
        "colorMode": "background",
        "graphMode": "area",
        "justifyMode": "auto",
        "orientation": "auto",
        "reduceOptions": {
          "calcs": ["lastNotNull"],
          "fields": "",
          "values": false
        },
        "textMode": "auto"
      },
      "pluginVersion": "10.0.0",
      "targets": [
        {
          "datasource": {
            "type": "loki",
            "uid": "Loki"
          },
          "editorMode": "code",
          "expr": "{service=\"slam-poker\"} |= \"Room statistics snapshot\" | json | unwrap total_active_users",
          "queryType": "",
          "refId": "A"
        }
      ],
      "title": "Active Users",
      "type": "stat"
    },
    {
      "datasource": {
        "type": "loki",
        "uid": "Loki"
      },
      "description": "Average room size across active rooms",
      "fieldConfig": {
        "defaults": {
          "color": {
            "mode": "thresholds"
          },
          "decimals": 1,
          "mappings": [],
          "thresholds": {
            "mode": "absolute",
            "steps": [
              {
                "color": "green",
                "value": null
              },
              {
                "color": "yellow",
                "value": 10
              },
              {
                "color": "red",
                "value": 20
              }
            ]
          },
          "unit": "short"
        },
        "overrides": []
      },
      "gridPos": {
        "h": 4,
        "w": 6,
        "x": 12,
        "y": 0
      },
      "id": 3,
      "options": {
        "colorMode": "background",
        "graphMode": "area",
        "justifyMode": "auto",
        "orientation": "auto",
        "reduceOptions": {
          "calcs": ["lastNotNull"],
          "fields": "",
          "values": false
        },
        "textMode": "auto"
      },
      "pluginVersion": "10.0.0",
      "targets": [
        {
          "datasource": {
            "type": "loki",
            "uid": "Loki"
          },
          "editorMode": "code",
          "expr": "{service=\"slam-poker\"} |= \"Room statistics snapshot\" | json | unwrap average_room_size",
          "queryType": "",
          "refId": "A"
        }
      ],
      "title": "Average Room Size",
      "type": "stat"
    },
    {
      "datasource": {
        "type": "loki",
        "uid": "Loki"
      },
      "description": "Number of rooms currently in voting state",
      "fieldConfig": {
        "defaults": {
          "color": {
            "mode": "thresholds"
          },
          "mappings": [],
          "thresholds": {
            "mode": "absolute",
            "steps": [
              {
                "color": "green",
                "value": null
              },
              {
                "color": "yellow",
                "value": 20
              },
              {
                "color": "red",
                "value": 50
              }
            ]
          },
          "unit": "short"
        },
        "overrides": []
      },
      "gridPos": {
        "h": 4,
        "w": 6,
        "x": 18,
        "y": 0
      },
      "id": 4,
      "options": {
        "colorMode": "background",
        "graphMode": "area",
        "justifyMode": "auto",
        "orientation": "auto",
        "reduceOptions": {
          "calcs": ["lastNotNull"],
          "fields": "",
          "values": false
        },
        "textMode": "auto"
      },
      "pluginVersion": "10.0.0",
      "targets": [
        {
          "datasource": {
            "type": "loki",
            "uid": "Loki"
          },
          "editorMode": "code",
          "expr": "{service=\"slam-poker\"} |= \"Room statistics snapshot\" | json | unwrap rooms_with_voting",
          "queryType": "",
          "refId": "A"
        }
      ],
      "title": "Rooms with Active Voting",
      "type": "stat"
    },
    {
      "datasource": {
        "type": "loki",
        "uid": "Loki"
      },
      "description": "Room creation and deletion rates over time",
      "fieldConfig": {
        "defaults": {
          "color": {
            "mode": "palette-classic"
          },
          "custom": {
            "axisCenteredZero": false,
            "axisColorMode": "text",
            "axisLabel": "",
            "axisPlacement": "auto",
            "barAlignment": 0,
            "drawStyle": "line",
            "fillOpacity": 10,
            "gradientMode": "none",
            "hideFrom": {
              "legend": false,
              "tooltip": false,
              "vis": false
            },
            "lineInterpolation": "linear",
            "lineWidth": 1,
            "pointSize": 5,
            "scaleDistribution": {
              "type": "linear"
            },
            "showPoints": "never",
            "spanNulls": false,
            "stacking": {
              "group": "A",
              "mode": "none"
            },
            "thresholdsStyle": {
              "mode": "off"
            }
          },
          "mappings": [],
          "thresholds": {
            "mode": "absolute",
            "steps": [
              {
                "color": "green",
                "value": null
              },
              {
                "color": "red",
                "value": 80
              }
            ]
          },
          "unit": "reqps"
        },
        "overrides": [
          {
            "matcher": {
              "id": "byName",
              "options": "Room Deletions"
            },
            "properties": [
              {
                "id": "color",
                "value": {
                  "mode": "fixed",
                  "fixedColor": "red"
                }
              }
            ]
          }
        ]
      },
      "gridPos": {
        "h": 8,
        "w": 12,
        "x": 0,
        "y": 4
      },
      "id": 5,
      "options": {
        "legend": {
          "calcs": [],
          "displayMode": "list",
          "placement": "bottom",
          "showLegend": true
        },
        "tooltip": {
          "mode": "multi",
          "sort": "none"
        }
      },
      "targets": [
        {
          "datasource": {
            "type": "loki",
            "uid": "Loki"
          },
          "editorMode": "code",
          "expr": "rate({service=\"slam-poker\"} |= \"Room created\" [5m])",
          "queryType": "",
          "refId": "A",
          "legendFormat": "Room Creations"
        },
        {
          "datasource": {
            "type": "loki",
            "uid": "Loki"
          },
          "editorMode": "code",
          "expr": "rate({service=\"slam-poker\"} |= \"Room deleted\" [5m])",
          "queryType": "",
          "refId": "B",
          "legendFormat": "Room Deletions"
        }
      ],
      "title": "Room Lifecycle",
      "type": "timeseries"
    },
    {
      "datasource": {
        "type": "loki",
        "uid": "Loki"
      },
      "description": "User engagement score distribution showing high vs low engagement sessions",
      "fieldConfig": {
        "defaults": {
          "color": {
            "mode": "palette-classic"
          },
          "custom": {
            "axisCenteredZero": false,
            "axisColorMode": "text",
            "axisLabel": "",
            "axisPlacement": "auto",
            "barAlignment": 0,
            "drawStyle": "line",
            "fillOpacity": 10,
            "gradientMode": "none",
            "hideFrom": {
              "legend": false,
              "tooltip": false,
              "vis": false
            },
            "lineInterpolation": "linear",
            "lineWidth": 1,
            "pointSize": 5,
            "scaleDistribution": {
              "type": "linear"
            },
            "showPoints": "never",
            "spanNulls": false,
            "stacking": {
              "group": "A",
              "mode": "none"
            },
            "thresholdsStyle": {
              "mode": "off"
            }
          },
          "mappings": [],
          "thresholds": {
            "mode": "absolute",
            "steps": [
              {
                "color": "green",
                "value": null
              },
              {
                "color": "red",
                "value": 80
              }
            ]
          },
          "unit": "short"
        },
        "overrides": []
      },
      "gridPos": {
        "h": 8,
        "w": 12,
        "x": 12,
        "y": 4
      },
      "id": 6,
      "options": {
        "legend": {
          "calcs": [],
          "displayMode": "list",
          "placement": "bottom",
          "showLegend": true
        },
        "tooltip": {
          "mode": "multi",
          "sort": "none"
        }
      },
      "targets": [
        {
          "datasource": {
            "type": "loki",
            "uid": "Loki"
          },
          "editorMode": "code",
          "expr": "{service=\"slam-poker\"} |= \"Session statistics snapshot\" | json | unwrap active_sessions",
          "queryType": "",
          "refId": "A",
          "legendFormat": "Active Sessions"
        },
        {
          "datasource": {
            "type": "loki",
            "uid": "Loki"
          },
          "editorMode": "code",
          "expr": "{service=\"slam-poker\"} |= \"Session statistics snapshot\" | json | unwrap high_engagement_sessions",
          "queryType": "",
          "refId": "B",
          "legendFormat": "High Engagement Sessions"
        }
      ],
      "title": "User Engagement Metrics",
      "type": "timeseries"
    },
    {
      "datasource": {
        "type": "loki",
        "uid": "Loki"
      },
      "description": "Average voting completion rate across all rooms",
      "fieldConfig": {
        "defaults": {
          "color": {
            "mode": "thresholds"
          },
          "decimals": 1,
          "mappings": [],
          "max": 100,
          "min": 0,
          "thresholds": {
            "mode": "absolute",
            "steps": [
              {
                "color": "red",
                "value": null
              },
              {
                "color": "yellow",
                "value": 70
              },
              {
                "color": "green",
                "value": 85
              }
            ]
          },
          "unit": "percent"
        },
        "overrides": []
      },
      "gridPos": {
        "h": 8,
        "w": 6,
        "x": 0,
        "y": 12
      },
      "id": 7,
      "options": {
        "orientation": "auto",
        "reduceOptions": {
          "calcs": ["lastNotNull"],
          "fields": "",
          "values": false
        },
        "showThresholdLabels": false,
        "showThresholdMarkers": true
      },
      "pluginVersion": "10.0.0",
      "targets": [
        {
          "datasource": {
            "type": "loki",
            "uid": "Loki"
          },
          "editorMode": "code",
          "expr": "{service=\"slam-poker\"} |= \"Votes revealed\" | json | unwrap voting_completion_rate",
          "queryType": "",
          "refId": "A"
        }
      ],
      "title": "Voting Completion Rate",
      "type": "gauge"
    },
    {
      "datasource": {
        "type": "loki",
        "uid": "Loki"
      },
      "description": "Average session duration in minutes",
      "fieldConfig": {
        "defaults": {
          "color": {
            "mode": "thresholds"
          },
          "decimals": 1,
          "mappings": [],
          "thresholds": {
            "mode": "absolute",
            "steps": [
              {
                "color": "red",
                "value": null
              },
              {
                "color": "yellow",
                "value": 10
              },
              {
                "color": "green",
                "value": 20
              }
            ]
          },
          "unit": "m"
        },
        "overrides": []
      },
      "gridPos": {
        "h": 8,
        "w": 6,
        "x": 6,
        "y": 12
      },
      "id": 8,
      "options": {
        "orientation": "auto",
        "reduceOptions": {
          "calcs": ["lastNotNull"],
          "fields": "",
          "values": false
        },
        "showThresholdLabels": false,
        "showThresholdMarkers": true
      },
      "pluginVersion": "10.0.0",
      "targets": [
        {
          "datasource": {
            "type": "loki",
            "uid": "Loki"
          },
          "editorMode": "code",
          "expr": "{service=\"slam-poker\"} |= \"Session statistics snapshot\" | json | unwrap average_session_duration_minutes",
          "queryType": "",
          "refId": "A"
        }
      ],
      "title": "Avg Session Duration",
      "type": "gauge"
    },
    {
      "datasource": {
        "type": "loki",
        "uid": "Loki"
      },
      "description": "Vote casting rate and patterns over time",
      "fieldConfig": {
        "defaults": {
          "color": {
            "mode": "palette-classic"
          },
          "custom": {
            "axisCenteredZero": false,
            "axisColorMode": "text",
            "axisLabel": "",
            "axisPlacement": "auto",
            "barAlignment": 0,
            "drawStyle": "line",
            "fillOpacity": 10,
            "gradientMode": "none",
            "hideFrom": {
              "legend": false,
              "tooltip": false,
              "vis": false
            },
            "lineInterpolation": "linear",
            "lineWidth": 1,
            "pointSize": 5,
            "scaleDistribution": {
              "type": "linear"
            },
            "showPoints": "never",
            "spanNulls": false,
            "stacking": {
              "group": "A",
              "mode": "none"
            },
            "thresholdsStyle": {
              "mode": "off"
            }
          },
          "mappings": [],
          "thresholds": {
            "mode": "absolute",
            "steps": [
              {
                "color": "green",
                "value": null
              },
              {
                "color": "red",
                "value": 80
              }
            ]
          },
          "unit": "reqps"
        },
        "overrides": []
      },
      "gridPos": {
        "h": 8,
        "w": 12,
        "x": 12,
        "y": 12
      },
      "id": 9,
      "options": {
        "legend": {
          "calcs": [],
          "displayMode": "list",
          "placement": "bottom",
          "showLegend": true
        },
        "tooltip": {
          "mode": "multi",
          "sort": "none"
        }
      },
      "targets": [
        {
          "datasource": {
            "type": "loki",
            "uid": "Loki"
          },
          "editorMode": "code",
          "expr": "rate({service=\"slam-poker\"} |= \"Vote cast\" [5m])",
          "queryType": "",
          "refId": "A",
          "legendFormat": "Vote Casts"
        },
        {
          "datasource": {
            "type": "loki",
            "uid": "Loki"
          },
          "editorMode": "code",
          "expr": "rate({service=\"slam-poker\"} |= \"Votes revealed\" [5m])",
          "queryType": "",
          "refId": "B",
          "legendFormat": "Vote Reveals"
        },
        {
          "datasource": {
            "type": "loki",
            "uid": "Loki"
          },
          "editorMode": "code",
          "expr": "rate({service=\"slam-poker\"} |= \"Next round started\" [5m])",
          "queryType": "",
          "refId": "C",
          "legendFormat": "Round Starts"
        }
      ],
      "title": "Voting Activity",
      "type": "timeseries"
    },
    {
      "datasource": {
        "type": "loki",
        "uid": "Loki"
      },
      "description": "Distribution of room sizes showing how many users are in rooms",
      "fieldConfig": {
        "defaults": {
          "color": {
            "mode": "palette-classic"
          },
          "custom": {
            "hideFrom": {
              "legend": false,
              "tooltip": false,
              "vis": false
            }
          },
          "mappings": []
        },
        "overrides": []
      },
      "gridPos": {
        "h": 8,
        "w": 12,
        "x": 0,
        "y": 20
      },
      "id": 10,
      "options": {
        "legend": {
          "displayMode": "list",
          "placement": "bottom",
          "showLegend": true
        },
        "pieType": "pie",
        "reduceOptions": {
          "calcs": ["lastNotNull"],
          "fields": "",
          "values": false
        },
        "tooltip": {
          "mode": "single",
          "sort": "none"
        }
      },
      "targets": [
        {
          "datasource": {
            "type": "loki",
            "uid": "Loki"
          },
          "editorMode": "code",
          "expr": "count by (room_size) ({service=\"slam-poker\"} |= \"User joined room\" | json | unwrap room_size)",
          "queryType": "",
          "refId": "A",
          "legendFormat": "{{room_size}} users"
        }
      ],
      "title": "Room Size Distribution",
      "type": "piechart"
    },
    {
      "datasource": {
        "type": "loki",
        "uid": "Loki"
      },
      "description": "Vote statistics showing averages and medians",
      "fieldConfig": {
        "defaults": {
          "color": {
            "mode": "palette-classic"
          },
          "custom": {
            "axisCenteredZero": false,
            "axisColorMode": "text",
            "axisLabel": "",
            "axisPlacement": "auto",
            "barAlignment": 0,
            "drawStyle": "line",
            "fillOpacity": 10,
            "gradientMode": "none",
            "hideFrom": {
              "legend": false,
              "tooltip": false,
              "vis": false
            },
            "lineInterpolation": "linear",
            "lineWidth": 1,
            "pointSize": 5,
            "scaleDistribution": {
              "type": "linear"
            },
            "showPoints": "never",
            "spanNulls": false,
            "stacking": {
              "group": "A",
              "mode": "none"
            },
            "thresholdsStyle": {
              "mode": "off"
            }
          },
          "mappings": [],
          "thresholds": {
            "mode": "absolute",
            "steps": [
              {
                "color": "green",
                "value": null
              },
              {
                "color": "red",
                "value": 80
              }
            ]
          },
          "unit": "short"
        },
        "overrides": []
      },
      "gridPos": {
        "h": 8,
        "w": 12,
        "x": 12,
        "y": 20
      },
      "id": 11,
      "options": {
        "legend": {
          "calcs": [],
          "displayMode": "list",
          "placement": "bottom",
          "showLegend": true
        },
        "tooltip": {
          "mode": "multi",
          "sort": "none"
        }
      },
      "targets": [
        {
          "datasource": {
            "type": "loki",
            "uid": "Loki"
          },
          "editorMode": "code",
          "expr": "avg_over_time({service=\"slam-poker\"} |= \"Votes revealed\" | json | unwrap vote_average [10m])",
          "queryType": "",
          "refId": "A",
          "legendFormat": "Vote Average"
        },
        {
          "datasource": {
            "type": "loki",
            "uid": "Loki"
          },
          "editorMode": "code",
          "expr": "avg_over_time({service=\"slam-poker\"} |= \"Votes revealed\" | json | unwrap vote_median [10m])",
          "queryType": "",
          "refId": "B",
          "legendFormat": "Vote Median"
        }
      ],
      "title": "Vote Statistics Trends",
      "type": "timeseries"
    }
  ],
  "refresh": "10s",
  "schemaVersion": 37,
  "style": "dark",
  "tags": ["slam-poker", "application", "business-metrics"],
  "templating": {
    "list": [
      {
        "current": {
          "selected": false,
          "text": "slam-poker",
          "value": "slam-poker"
        },
        "datasource": {
          "type": "loki",
          "uid": "Loki"
        },
        "definition": "label_values(service)",
        "hide": 0,
        "includeAll": false,
        "label": "Service",
        "multi": false,
        "name": "service",
        "options": [],
        "query": "label_values(service)",
        "refresh": 1,
        "regex": "",
        "skipUrlSync": false,
        "sort": 0,
        "type": "query"
      },
      {
        "current": {
          "selected": false,
          "text": "production",
          "value": "production"
        },
        "datasource": {
          "type": "loki",
          "uid": "Loki"
        },
        "definition": "label_values({service=\"$service\"}, environment)",
        "hide": 0,
        "includeAll": false,
        "label": "Environment",
        "multi": false,
        "name": "environment",
        "options": [],
        "query": "label_values({service=\"$service\"}, environment)",
        "refresh": 1,
        "regex": "",
        "skipUrlSync": false,
        "sort": 0,
        "type": "query"
      },
      {
        "current": {
          "selected": true,
          "text": ["All"],
          "value": ["$__all"]
        },
        "datasource": {
          "type": "loki",
          "uid": "Loki"
        },
        "definition": "label_values({service=\"$service\"} |= \"roomCode\", roomCode)",
        "hide": 0,
        "includeAll": true,
        "label": "Room Code",
        "multi": true,
        "name": "roomCode",
        "options": [],
        "query": "label_values({service=\"$service\"} |= \"roomCode\", roomCode)",
        "refresh": 1,
        "regex": "",
        "skipUrlSync": false,
        "sort": 0,
        "type": "query"
      }
    ]
  },
  "time": {
    "from": "now-1h",
    "to": "now"
  },
  "timepicker": {},
  "timezone": "",
  "title": "SLAM Poker - Application Metrics",
  "uid": "slam-poker-application-metrics",
  "version": 1,
  "weekStart": ""
}
